ml_switching_reg/__init__.py
ml_switching_reg/cm.py
ml_switching_reg/mle.py
ml_switching_reg/patches.py
ml_switching_reg-0.15.5.dist-info/METADATA
ml_switching_reg-0.15.5.dist-info/WHEEL
ml_switching_reg-0.15.5.dist-info/RECORD
